pydffi/__init__.py
pydffi/backend.cpython-37m-darwin.so
pydffi/purectypes_generator/__init__.py
pydffi/purectypes_generator/generator.py
pydffi-0.9.3.dist-info/LICENSE.txt
pydffi-0.9.3.dist-info/METADATA
pydffi-0.9.3.dist-info/WHEEL
pydffi-0.9.3.dist-info/entry_points.txt
pydffi-0.9.3.dist-info/top_level.txt
pydffi-0.9.3.dist-info/RECORD
