Metadata-Version: 2.1
Name: pydffi
Version: 0.9.3
Summary: dragonffi static python bindings
Home-page: https://github.com/aguinet/dragonffi
Author: Adrien Guinet
Author-email: adrien@guinet.me
License: Apache 2.0
Download-URL: https://github.com/aguinet/dragonffi/tarball/dffi-0.9.3
Keywords: ffi clang llvm
Platform: UNKNOWN
Classifier: Development Status :: 5 - Production/Stable
Classifier: Intended Audience :: Science/Research
Classifier: Intended Audience :: Developers
Classifier: Topic :: Software Development :: Build Tools
Classifier: Topic :: Scientific/Engineering
Classifier: License :: OSI Approved :: Apache Software License
Classifier: Programming Language :: Python :: 2
Classifier: Programming Language :: Python :: 2.7
Classifier: Programming Language :: Python :: 3
Classifier: Programming Language :: Python :: 3.4
Classifier: Programming Language :: Python :: 3.5
Classifier: Programming Language :: Python :: 3.6
Classifier: Programming Language :: Python :: 3.7
Classifier: Programming Language :: Python :: 3.8
Classifier: Programming Language :: Python :: 3.9
Requires-Python: >=2.7, !=3.0.*, !=3.1.*, !=3.2.*, <4
License-File: LICENSE.txt
